README.rst
setup.cfg
setup.py
faker_job_brazil.egg-info/PKG-INFO
faker_job_brazil.egg-info/SOURCES.txt
faker_job_brazil.egg-info/dependency_links.txt
faker_job_brazil.egg-info/not-zip-safe
faker_job_brazil.egg-info/requires.txt
faker_job_brazil.egg-info/top_level.txt
src/job/__init__.py