Metadata-Version: 1.1
Name: faker-job-brazil
Version: 0.0.1.dev0
Summary: Brazilian Job Provider for the Faker Python package.
Home-page: https://github.com/paladini/faker_job_brazil
Author: paladini
Author-email: fnpaladini+fakerjobbrazil@gmail.com
License: Apache License, Version 2.0
Keywords: faker test data brazil job emprego profissão
Platform: any
Classifier: Development Status :: 3 - Alpha
Classifier: Environment :: Console
Classifier: Intended Audience :: Developers
Classifier: Programming Language :: Python
Classifier: Programming Language :: Python :: 2
Classifier: Programming Language :: Python :: 2.7
Classifier: Programming Language :: Python :: 3
Classifier: Programming Language :: Python :: 3.3
Classifier: Programming Language :: Python :: 3.4
Classifier: Programming Language :: Python :: 3.5
Classifier: Programming Language :: Python :: 3.6
Classifier: Programming Language :: Python :: Implementation :: PyPy
Classifier: Topic :: Software Development :: Libraries :: Python Modules
Classifier: Topic :: Software Development :: Testing
Classifier: Topic :: Utilities
Classifier: License :: OSI Approved :: Apache Software License
